pyramid_recaptcha
