Metadata-Version: 1.1
Name: pyramid-recaptcha
Version: 1.0.2
Summary: A pyramid/deform widget implementing googles recaptcha widget.
Home-page: https://github.com/pretagov/pyramid_recaptcha.git
Author: Jon Pentland, PretaGov Ltd
Author-email: jon.pentland@pretagov.co.uk
License: UNKNOWN
Keywords: pyramid deform recaptcha captcha
Platform: UNKNOWN
Classifier: Environment :: Web Environment
Classifier: Framework :: Pylons
Classifier: Framework :: Pyramid
Classifier: Intended Audience :: Developers
Classifier: License :: OSI Approved :: GNU General Public License v3 (GPLv3)
Classifier: Operating System :: OS Independent
Classifier: Programming Language :: Python
Classifier: Programming Language :: Python :: 2.7
Classifier: Topic :: Internet :: WWW/HTTP
Classifier: Topic :: Software Development :: User Interfaces
